{"orderbooks":[{"baseAsset":"SOL","bids":[{"price":134,"quantity":5,"orderId":"8vnl73m6nif7dog9ao1nn","filled":0,"side":"buy","userId":"1"},{"price":139,"quantity":4,"orderId":"ryrmk5wr82bd4p1f0j31m","filled":0,"side":"buy","userId":"1"},{"price":139,"quantity":4,"orderId":"mkgwi5ths3cffaz9o3ympk","filled":0,"side":"buy","userId":"111643307326981211990"},{"price":135,"quantity":3,"orderId":"rbonaia8ma3x2cqn21zk7","filled":0,"side":"buy","userId":"111643307326981211990"},{"price":138,"quantity":1,"orderId":"7x3hk2babxhly69uo6ip","filled":0,"side":"buy","userId":"111643307326981211990"},{"price":138,"quantity":1,"orderId":"z1ksfib7xza9uz286c5w8i","filled":0,"side":"buy","userId":"111643307326981211990"},{"price":138,"quantity":1,"orderId":"h7e7c9rhsf8xw745onn4l","filled":0,"side":"buy","userId":"111643307326981211990"},{"price":138,"quantity":1,"orderId":"rfwl8uionqughcjfp08o","filled":0,"side":"buy","userId":"111643307326981211990"},{"price":138,"quantity":1,"orderId":"4hzbcjk3jesbvgb4csszow","filled":0,"side":"buy","userId":"111643307326981211990"},{"price":139,"quantity":2,"orderId":"dddeoi6xj05gzrivsqton","filled":0,"side":"buy","userId":"111643307326981211990"},{"price":135,"quantity":2,"orderId":"bcq4rnhg6g0484qmirqsxh","filled":0,"side":"buy","userId":"4"},{"price":135,"quantity":2,"orderId":"ctqdc3z7e665pgh7oteha5","filled":0,"side":"buy","userId":"4"},{"price":135,"quantity":1,"orderId":"ouhz9mu3rwo8eegaye74","filled":0,"side":"buy","userId":"4"},{"price":135,"quantity":1,"orderId":"k1nekjvkx1mx3iyw4z03e","filled":0,"side":"buy","userId":"4"}],"asks":[{"price":146,"quantity":2,"orderId":"lo2tt50406p0a3yfo8f6","filled":0,"side":"sell","userId":"2"},{"price":148,"quantity":2,"orderId":"n5wa8qk6heuj3a4rp7znp","filled":0,"side":"sell","userId":"2"},{"price":143.87,"quantity":5,"orderId":"3ntuqin4vw3yqyqhahsqri","filled":0,"side":"sell","userId":"2"},{"price":140,"quantity":5,"orderId":"uyn8yk9hojvw23f4a69g","filled":4,"side":"sell","userId":"1"},{"price":142,"quantity":3,"orderId":"uht98f9q36h0rob57vfwayf","filled":2,"side":"sell","userId":"111643307326981211990"},{"price":143,"quantity":4,"orderId":"2amijbr8gkuooaas116l3b","filled":0,"side":"sell","userId":"111643307326981211990"},{"price":145,"quantity":2,"orderId":"rtozp8fg9q940v01fu4g14","filled":0,"side":"sell","userId":"111643307326981211990"}],"lastTradeId":15,"currentPrice":140},{"baseAsset":"BTC","bids":[],"asks":[{"price":62634,"quantity":5,"orderId":"b7vz572cl7v1c0jtx7p1u8","filled":0,"side":"sell","userId":"1"}],"lastTradeId":8,"currentPrice":62580},{"baseAsset":"ETH","bids":[{"price":21,"quantity":12,"orderId":"cvhn0imbv86t3wfspygwi","filled":0,"side":"buy","userId":"117749744289673088067"},{"price":21,"quantity":12,"orderId":"qly9watezdduqwuho3gtm","filled":0,"side":"buy","userId":"117749744289673088067"},{"price":21,"quantity":12,"orderId":"914q6f2cyyhwqap3wqvdi","filled":0,"side":"buy","userId":"117749744289673088067"}],"asks":[{"price":21,"quantity":12,"orderId":"xm6ntg7irm6b2pr849oqd","filled":11,"side":"sell","userId":"117749744289673088067"}],"lastTradeId":20,"currentPrice":2441},{"baseAsset":"UNI","bids":[{"price":7.15,"quantity":2,"orderId":"m5klie42bbcasndw6xwy5","filled":1,"side":"buy","userId":"1"},{"price":7.2,"quantity":3,"orderId":"nle18js8s3j5n5avzr3ist","filled":2,"side":"buy","userId":"1"}],"asks":[{"price":7.35,"quantity":2,"orderId":"ikw46hqbzbgol3om3p5jh","filled":0,"side":"sell","userId":"2"},{"price":7.33,"quantity":2,"orderId":"5jfbo8klo1qiow6ydwxbw8","filled":0,"side":"sell","userId":"2"},{"price":7.38,"quantity":2,"orderId":"0lm6bstuhphcy4xc5wvuw","filled":0,"side":"sell","userId":"2"},{"price":7.4,"quantity":2,"orderId":"99i6bagm1qoesl2l3ux7m5","filled":0,"side":"sell","userId":"2"}],"lastTradeId":6,"currentPrice":7.15},{"baseAsset":"LINK","bids":[{"price":11.2,"quantity":4,"orderId":"fp7ekg05yje93q7wdonb6n","filled":0,"side":"buy","userId":"1"},{"price":11.12,"quantity":3,"orderId":"3j08hoqym16or38434mho","filled":0,"side":"buy","userId":"1"},{"price":11.23,"quantity":5,"orderId":"mohda5mp1ok3k8tgrfq4x8","filled":2,"side":"buy","userId":"1"},{"price":0,"quantity":1,"orderId":"foe91t6wxtt4fw0x6emiuw","filled":0,"side":"buy","userId":"111643307326981211990"},{"price":11.3,"quantity":2,"orderId":"xocogcs5iyxhm0i0sm73","filled":0,"side":"buy","userId":"111643307326981211990"},{"price":11.2,"quantity":2,"orderId":"w77gpg5gz6vzmhl1890v9","filled":0,"side":"buy","userId":"111643307326981211990"}],"asks":[{"price":11.4,"quantity":2,"orderId":"4b19sd2yk9yd4c8yn2rhm","filled":0,"side":"sell","userId":"2"},{"price":11.41,"quantity":4,"orderId":"9lhz75puyvb4c0p3nkr423","filled":0,"side":"sell","userId":"2"},{"price":11.36,"quantity":3,"orderId":"j1xp0wncdrv0d7h922gpb","filled":0,"side":"sell","userId":"2"}],"lastTradeId":13,"currentPrice":11.33}],"balances":[["1",{"USDC":{"available":9629132.269999998,"locked":238.31999999997788},"BTC":{"available":10000000,"locked":5},"SOL":{"available":10000014,"locked":-4},"ETH":{"available":10000023,"locked":0},"UNI":{"available":10000009,"locked":0},"LINK":{"available":10000017,"locked":0}}],["2",{"USDC":{"available":10108397.090000004,"locked":5},"BTC":{"available":9999999,"locked":0},"SOL":{"available":9999987,"locked":1},"ETH":{"available":9999982,"locked":0},"UNI":{"available":9999983,"locked":8},"LINK":{"available":9999961,"locked":22}}],["5",{"USDC":{"available":10000000,"locked":0},"BTC":{"available":10000000,"locked":0},"SOL":{"available":10000000,"locked":0},"ETH":{"available":10000000,"locked":0},"UNI":{"available":10000000,"locked":0},"LINK":{"available":10000000,"locked":0}}],["111643307326981211990",{"USDC":{"available":9983688.64,"locked":1996.6800000000003},"BTC":{"available":10000000,"locked":0},"SOL":{"available":9999995,"locked":7},"ETH":{"available":10000006,"locked":0},"UNI":{"available":10000000,"locked":0},"HNT":{"available":10000000,"locked":0}}],["4",{"USDC":{"available":9498472,"locked":837},"BTC":{"available":10000008,"locked":0},"SOL":{"available":10000000,"locked":0},"ETH":{"available":10000000,"locked":0},"UNI":{"available":10000000,"locked":0},"HNT":{"available":10000000,"locked":0}}],["117749744289673088067",{"USDC":{"available":10777106,"locked":756},"BTC":{"available":9999988,"locked":0},"SOL":{"available":10000000,"locked":0},"ETH":{"available":9999988,"locked":1},"UNI":{"available":10000000,"locked":0},"HNT":{"available":10000000,"locked":0}}]]}